vec2tif/__init__.py
vec2tif/__main__.py
vec2tif/csv2tif.py
vec2tif/fgd2tif.py
vec2tif/shp2tif.py
vec2tif-0.2.1.dist-info/METADATA
vec2tif-0.2.1.dist-info/WHEEL
vec2tif-0.2.1.dist-info/licenses/LICENSE
vec2tif-0.2.1.dist-info/RECORD
