Metadata-Version: 2.1
Name: vec2tif
Version: 0.2.1
Summary: Conversion of vector data to GeoTIFF
Author-email: Kiwamu Ishikura <ishikura.kiwamu@gmail.com>
License: MIT License
License-File: LICENSE
Classifier: License :: OSI Approved :: MIT License
Classifier: Operating System :: OS Independent
Classifier: Programming Language :: Python :: 3
Requires-Python: >=3.7
Requires-Dist: gdal
Requires-Dist: geopandas
Requires-Dist: haversine
Requires-Dist: numpy
Requires-Dist: pyproj
Requires-Dist: rasterio
Requires-Dist: shapely
Provides-Extra: dev
Requires-Dist: build; extra == 'dev'
Requires-Dist: twine; extra == 'dev'
